ai_tools_zxw/__init__.py
ai_tools_zxw/plp_install.py
ai_tools_zxw/大语言模型提示词.py
ai_tools_zxw/查看编辑coco标注.py
ai_tools_zxw/LLM_API/__init__.py
ai_tools_zxw/LLM_API/config.py
ai_tools_zxw/LLM_API/LLM_BaiDu/__init__.py
ai_tools_zxw/LLM_API/LLM_BaiDu/多轮对话_http.py
ai_tools_zxw/LLM_API/LLM_Claude/__init__.py
ai_tools_zxw/LLM_API/LLM_Claude/chat.py
ai_tools_zxw/LLM_API/LLM_OpenAI/__init__.py
ai_tools_zxw/LLM_API/LLM_OpenAI/多轮对话_http.py
ai_tools_zxw/LLM_API/LLM_ifly/__init__.py
ai_tools_zxw/LLM_API/LLM_ifly/api/__init__.py
ai_tools_zxw/LLM_API/LLM_ifly/api/General/__init__.py
ai_tools_zxw/LLM_API/LLM_ifly/api/General/多轮对话_http.py
ai_tools_zxw/LLM_API/LLM_ifly/api/General/chat/Chat.py
ai_tools_zxw/LLM_API/LLM_ifly/api/General/chat/__SparkApi.py
ai_tools_zxw/LLM_API/LLM_ifly/api/General/chat/__init__.py
ai_tools_zxw/LLM_API/LLM_ifly/api/selfLLM/__init__.py
ai_tools_zxw/LLM_API/LLM_ifly/api/selfLLM/单句对话_ws_回调式.py
ai_tools_zxw/LLM_API/LLM_ifly/api/selfLLM/单句对话_ws_阻塞式.py
ai_tools_zxw/LLM_API/LLM_ifly/prepare_train_data/__init__.py
ai_tools_zxw/LLM_API/LLM_ifly/prepare_train_data/pd2jonsl.py
ai_tools_zxw/LLM_API/LLM_ifly/prepare_train_data/to_jsonl.py
ai_tools_zxw/LLM_API/LLM_通义千问/__init__.py
ai_tools_zxw/LLM_API/LLM_通义千问/多轮对话_http.py
ai_tools_zxw/data_anay/__init__.py
ai_tools_zxw/data_anay/kmeans.py
ai_tools_zxw/data_anay/polyfit.py
ai_tools_zxw/data_preprocessing/__init__.py
ai_tools_zxw/data_preprocessing/image/__init__.py
ai_tools_zxw/data_preprocessing/image/多张图片_合成_视频.py
ai_tools_zxw/data_preprocessing/image/视频_提取_帧图片.py
ai_tools_zxw/data_preprocessing/nlp/__init__.py
ai_tools_zxw/data_preprocessing/nlp/pre_process.py
ai_tools_zxw/data_preprocessing/nlp/remove_error_encode.py
ai_tools_zxw/data_preprocessing/测试/__init__.py
ai_tools_zxw/data_preprocessing/测试/process测试.py
ai_tools_zxw/data_preprocessing/测试/txt转epub.py
ai_tools_zxw/data_visualize/__init__.py
ai_tools_zxw/data_visualize/多图标.py
ai_tools_zxw/data_visualize/折线图.py
ai_tools_zxw/data_visualize/柱状图.py
ai_tools_zxw-2.8.25.dist-info/METADATA
ai_tools_zxw-2.8.25.dist-info/WHEEL
ai_tools_zxw-2.8.25.dist-info/top_level.txt
ai_tools_zxw-2.8.25.dist-info/RECORD
