Metadata-Version: 2.1
Name: ai-tools-zxw
Version: 2.8.25
Summary: 薛伟的AI工具集
Home-page: https://github.com/sunshineinwater/
Author: xue wei zhang
Author-email: 
Classifier: Programming Language :: Python :: 3.10
Classifier: License :: OSI Approved :: MIT License
Classifier: Operating System :: OS Independent
Requires-Dist: xlwt
Requires-Dist: psutil
Requires-Dist: openai
